tc_neo4j_lib/__init__.py
tc_neo4j_lib/credentials.py
tc_neo4j_lib/neo4j_ops.py
tc_neo4j_lib/schema.py
tests/__init__.py
tests/integration/__init__.py
tests/integration/test_run_queries.py
tests/unit/__init__.py
tests/unit/test_credentials.py
tc_neo4j_lib-2.0.4.dist-info/METADATA
tc_neo4j_lib-2.0.4.dist-info/WHEEL
tc_neo4j_lib-2.0.4.dist-info/top_level.txt
tc_neo4j_lib-2.0.4.dist-info/RECORD
