Metadata-Version: 2.1
Name: tc-neo4j-lib
Version: 2.0.4
Summary: A neo4j shared library to use across togethercrew python projects.
Author: Mohammad Amin Dadgar, TogetherCrew
Maintainer: Mohammad Amin Dadgar
Maintainer-email: dadgaramin96@gmail.com
Requires-Dist: numpy>=1.24.1
Requires-Dist: pytest<8.0.0,>=7.2.0
Requires-Dist: pytest-cov<5.0.0,>=4.0.0
Requires-Dist: coverage<8.0.0,>=7.2.5
Requires-Dist: python-dotenv<2.0.0,>=1.0.0
Requires-Dist: neo4j<6.0.0,>=5.22.0
Requires-Dist: graphdatascience<2.0.0,>=1.10.0
